dtrx/__init__.py
dtrx/dtrx.py
dtrx-8.7.0.dist-info/licenses/COPYING
dtrx-8.7.0.dist-info/METADATA
dtrx-8.7.0.dist-info/WHEEL
dtrx-8.7.0.dist-info/entry_points.txt
dtrx-8.7.0.dist-info/top_level.txt
dtrx-8.7.0.dist-info/RECORD
