Metadata-Version: 2.4
Name: dtrx
Version: 8.7.0
Summary: Script to intelligently extract multiple archive types
Author-email: Brett Smith <brettcsmith@brettcsmith.org>
Maintainer-email: Brett Smith <brettcsmith@brettcsmith.org>
License-Expression: GPL-3.0-or-later
Project-URL: Homepage, http://www.brettcsmith.org/2007/dtrx/
Project-URL: Repository, https://github.com/dtrx-py/dtrx
Project-URL: Download, https://github.com/dtrx-py/dtrx
Classifier: Development Status :: 5 - Production/Stable
Classifier: Environment :: Console
Classifier: Intended Audience :: End Users/Desktop
Classifier: Intended Audience :: System Administrators
Classifier: Natural Language :: English
Classifier: Operating System :: POSIX
Classifier: Programming Language :: Python
Classifier: Programming Language :: Python :: 3
Classifier: Programming Language :: Python :: Implementation :: CPython
Classifier: Topic :: Utilities
Requires-Python: >=3.10
License-File: COPYING
Requires-Dist: unsupported-python==1.0.0; platform_system == "Windows"
Dynamic: license-file
